pyarabify/__init__.py
pyarabify/__main__.py
pyarabify/dat/dial.json
pyarabify/dat/dict.json
pyarabify/dat/dict_ext.json
pyarabify/dat/msgs.json
pyarabify/dat/msgs_ext.json
pyarabify/examples/الأصناف.py
pyarabify/examples/الحلقات.py
pyarabify/examples/الدوال.py
pyarabify/examples/الشروط.py
pyarabify/examples/القوائم.py
pyarabify/examples/المتغيرات.py
pyarabify/src/__init__.py
pyarabify/src/aut.py
pyarabify/src/cvt.py
pyarabify/src/doc.py
pyarabify/src/drw.py
pyarabify/src/edat.py
pyarabify/src/err.py
pyarabify/src/exe.py
pyarabify/src/ghb.py
pyarabify/src/git.py
pyarabify/src/hlp.py
pyarabify/src/imp.py
pyarabify/src/lib.py
pyarabify/src/mth.py
pyarabify/src/pkg.py
pyarabify/src/prj.py
pyarabify/src/prs.py
pyarabify/src/spl.py
pyarabify/src/vid.py
pyarabify/src/web.py
pyarabify-2.2.0.dist-info/licenses/LICENSE
pyarabify-2.2.0.dist-info/METADATA
pyarabify-2.2.0.dist-info/WHEEL
pyarabify-2.2.0.dist-info/entry_points.txt
pyarabify-2.2.0.dist-info/top_level.txt
pyarabify-2.2.0.dist-info/RECORD
