Metadata-Version: 2.4
Name: pyarabify
Version: 2.2.0
Summary: مكتبة قوية لتحويل لغة Python كاملة إلى العربية مع دعم اللهجات المختلفة
Home-page: https://github.com/6x-u/pyarabify
Author: MERO
Author-email: 
License: MIT
Project-URL: Homepage, https://github.com/6x-u/pyarabify
Project-URL: Repository, https://github.com/6x-u/pyarabify
Project-URL: Bug Tracker, https://github.com/6x-u/pyarabify/issues
Project-URL: Telegram, https://t.me/QP4RM
Keywords: arabic,python,interpreter,localization,translation,عربي,بايثون
Classifier: Development Status :: 5 - Production/Stable
Classifier: Intended Audience :: Developers
Classifier: Intended Audience :: Education
Classifier: Programming Language :: Python :: 2.7
Classifier: Programming Language :: Python :: 3
Classifier: Natural Language :: Arabic
Requires-Python: >=2.7
License-File: LICENSE
Dynamic: home-page
Dynamic: license-file
Dynamic: requires-python
